cfcommander/__about__.py
cfcommander/__init__.py
cfcommander/__main__.py
cfcommander-0.1.15.dist-info/METADATA
cfcommander-0.1.15.dist-info/WHEEL
cfcommander-0.1.15.dist-info/entry_points.txt
cfcommander-0.1.15.dist-info/licenses/LICENSE
cfcommander-0.1.15.dist-info/RECORD
