Metadata-Version: 2.4
Name: cfcommander
Version: 0.1.15
Summary: A simple Cloudflare DNS CLI tool
Author-email: Jakub Jim Zacek <jakub@zacekj.cz>
License-Expression: MIT
License-File: LICENSE
Requires-Python: >=3.8
Requires-Dist: requests
Requires-Dist: tabulate
